qi_utilities/__init__.py
qi_utilities/algorithms/__init__.py
qi_utilities/algorithms/trotterization.py
qi_utilities/classical_solvers/__init__.py
qi_utilities/classical_solvers/time_evolution.py
qi_utilities/factsheets/__init__.py
qi_utilities/notebook_guides/__init__.py
qi_utilities/notebook_guides/figures/__init__.py
qi_utilities/utility_functions/__init__.py
qi_utilities/utility_functions/api_legacy_functions.py
qi_utilities/utility_functions/circuit_modifiers.py
qi_utilities/utility_functions/data_handling.py
qi_utilities/utility_functions/quantum_info.py
qi_utilities/utility_functions/raw_data_processing.py
qi_utilities/utility_functions/readout_correction.py
qi_utilities-0.2.1.dist-info/licenses/LICENSE
qi_utilities-0.2.1.dist-info/METADATA
qi_utilities-0.2.1.dist-info/WHEEL
qi_utilities-0.2.1.dist-info/top_level.txt
qi_utilities-0.2.1.dist-info/RECORD
