Metadata-Version: 2.4
Name: qi-utilities
Version: 0.2.1
Summary: Package library with utility functions and demonstration notebooks especially suited for the superconducting hardware backends of the cloud quantum computing platform Quantum Inspire.
Author-email: DiCarlo Lab at QuTech <secr-qutech@tudelft.nl>
Maintainer-email: Marios Samiotis <m.samiotis@tudelft.nl>
License-Expression: MIT
Project-URL: Homepage, https://github.com/DiCarloLab-Delft/QuantumInspireUtilities
Keywords: quantuminspire,qiskit,quantum computing,superconducting
Classifier: Development Status :: 3 - Alpha
Classifier: Intended Audience :: Science/Research
Classifier: Programming Language :: Python :: 3 :: Only
Classifier: Programming Language :: Python :: 3.9
Classifier: Programming Language :: Python :: 3.10
Classifier: Programming Language :: Python :: 3.11
Classifier: Programming Language :: Python :: 3.12
Classifier: Topic :: Scientific/Engineering
Requires-Python: >=3.9
License-File: LICENSE
Requires-Dist: qiskit-quantuminspire
Requires-Dist: matplotlib
Requires-Dist: pandas
Requires-Dist: pylatexenc
Requires-Dist: qiskit-qasm3-import
Requires-Dist: h5py
Dynamic: license-file
